usbpdpy-0.2.1.dist-info/METADATA
usbpdpy-0.2.1.dist-info/WHEEL
usbpdpy-0.2.1.dist-info/licenses/LICENSE
usbpdpy/__init__.py
usbpdpy/usbpdpy.cpython-312-x86_64-linux-gnu.so
usbpdpy-0.2.1.dist-info/RECORD
