Metadata-Version: 2.4
Name: usbpdpy
Version: 0.2.1
Classifier: Development Status :: 4 - Beta
Classifier: Intended Audience :: Developers
Classifier: Intended Audience :: Science/Research
Classifier: Topic :: System :: Hardware :: Universal Serial Bus (USB)
Classifier: Topic :: Scientific/Engineering :: Electronic Design Automation (EDA)
Classifier: Topic :: Software Development :: Libraries :: Python Modules
Classifier: License :: OSI Approved :: MIT License
Classifier: Programming Language :: Python :: 3
Classifier: Programming Language :: Python :: 3.8
Classifier: Programming Language :: Python :: 3.9
Classifier: Programming Language :: Python :: 3.10
Classifier: Programming Language :: Python :: 3.11
Classifier: Programming Language :: Python :: 3.12
Classifier: Programming Language :: Rust
Classifier: Programming Language :: Python :: Implementation :: CPython
License-File: LICENSE
Summary: Python bindings for USB Power Delivery protocol message parsing
Keywords: usb,usb-pd,power-delivery,protocol,parsing,hardware
Home-Page: https://github.com/okhsunrog/usbpdpy
Author-email: Danila Gornushko <me@okhsunrog.dev>
License: MIT
Requires-Python: >=3.8
Project-URL: Homepage, https://github.com/okhsunrog/usbpdpy
Project-URL: Repository, https://github.com/okhsunrog/usbpdpy
Project-URL: Issues, https://github.com/okhsunrog/usbpdpy/issues
Project-URL: Documentation, https://github.com/okhsunrog/usbpdpy#readme
